{
  "manifestVersion": "3.2",
  "admin": {
    "address": "0x9C850442c0c8C8A4920Bb7502D87E7d9Dd974dF1",
    "txHash": "0x4b963dd82f42a9cd51b1c9ff3d35323cdd90cb3c908fdb9b876e94df6059881d"
  },
  "proxies": [
    {
      "address": "0xD890F2D60B429f9e257FC0Bc58Ef2237776DD91B",
      "txHash": "0xff632da0606c4441a5b2379160c66a9de959a3dedc4dde26611e9dbe7c4a4cb1",
      "kind": "transparent"
    }
  ],
  "impls": {
    "aa2ebfdc402a17c9975b61a1ee2c1f693a477beea18e8fb8265bd6815a43ceba": {
      "address": "0x3A2972dE721C8EBF521bA2Ce7A21F59f6caA1623",
      "txHash": "0x1edbab15c14903570da09cf98de8cc394e7fedfb3c31ff280126dfd7b12eb5a1",
      "layout": {
        "storage": [
          {
            "contract": "Initializable",
            "label": "_initialized",
            "type": "t_bool",
            "src": "../@openzeppelin/contracts-upgradeable/proxy/utils/Initializable.sol:39"
          },
          {
            "contract": "Initializable",
            "label": "_initializing",
            "type": "t_bool",
            "src": "../@openzeppelin/contracts-upgradeable/proxy/utils/Initializable.sol:44"
          },
          {
            "contract": "RevocationRegistry",
            "label": "registry",
            "type": "t_mapping(t_address,t_struct(WalletRevocationRegistry)401_storage)",
            "src": "../project:/contracts/RevocationRegistry.sol:26"
          }
        ],
        "types": {
          "t_mapping(t_address,t_struct(WalletRevocationRegistry)401_storage)": {
            "label": "mapping(address => struct RevocationRegistry.WalletRevocationRegistry)"
          },
          "t_address": {
            "label": "address"
          },
          "t_struct(WalletRevocationRegistry)401_storage": {
            "label": "struct RevocationRegistry.WalletRevocationRegistry",
            "members": [
              {
                "label": "walletInRegistry",
                "type": "t_bool"
              },
              {
                "label": "totalLists",
                "type": "t_uint256"
              },
              {
                "label": "listIdUsage",
                "type": "t_mapping(t_uint256,t_bool)"
              },
              {
                "label": "lists",
                "type": "t_mapping(t_uint256,t_array(t_uint256)dyn_storage)"
              }
            ]
          },
          "t_bool": {
            "label": "bool"
          },
          "t_uint256": {
            "label": "uint256"
          },
          "t_mapping(t_uint256,t_bool)": {
            "label": "mapping(uint256 => bool)"
          },
          "t_mapping(t_uint256,t_array(t_uint256)dyn_storage)": {
            "label": "mapping(uint256 => uint256[])"
          },
          "t_array(t_uint256)dyn_storage": {
            "label": "uint256[]"
          }
        }
      }
    },
    "e27561195d8bf9de896372c7eb4adb60cad2f50abf5f86b8099deae57c362fd2": {
      "address": "0x05CE33cF2970117741468E19Df0D993A4DEE7bBF",
      "txHash": "0xea0960dab465c2cd03e23ce9a049875cb3cc11da7b2460f2f0526d140f20994e",
      "layout": {
        "storage": [
          {
            "contract": "Initializable",
            "label": "_initialized",
            "type": "t_uint8",
            "src": "../@openzeppelin/contracts-upgradeable/proxy/utils/Initializable.sol:62",
            "retypedFrom": "bool"
          },
          {
            "contract": "Initializable",
            "label": "_initializing",
            "type": "t_bool",
            "src": "../@openzeppelin/contracts-upgradeable/proxy/utils/Initializable.sol:67"
          },
          {
            "contract": "RevocationRegistry",
            "label": "registry",
            "type": "t_mapping(t_address,t_struct(WalletRevocationRegistry)841_storage)",
            "src": "../project:/contracts/RevocationRegistry.sol:27"
          },
          {
            "contract": "RevocationRegistry",
            "label": "permissions",
            "type": "t_contract(Permissions)757",
            "src": "../project:/contracts/RevocationRegistry.sol:29"
          }
        ],
        "types": {
          "t_mapping(t_address,t_struct(WalletRevocationRegistry)841_storage)": {
            "label": "mapping(address => struct RevocationRegistry.WalletRevocationRegistry)"
          },
          "t_address": {
            "label": "address"
          },
          "t_struct(WalletRevocationRegistry)841_storage": {
            "label": "struct RevocationRegistry.WalletRevocationRegistry",
            "members": [
              {
                "label": "walletInRegistry",
                "type": "t_bool"
              },
              {
                "label": "totalLists",
                "type": "t_uint256"
              },
              {
                "label": "listIdUsage",
                "type": "t_mapping(t_uint256,t_bool)"
              },
              {
                "label": "lists",
                "type": "t_mapping(t_uint256,t_array(t_uint256)dyn_storage)"
              }
            ]
          },
          "t_bool": {
            "label": "bool"
          },
          "t_uint256": {
            "label": "uint256"
          },
          "t_mapping(t_uint256,t_bool)": {
            "label": "mapping(uint256 => bool)"
          },
          "t_mapping(t_uint256,t_array(t_uint256)dyn_storage)": {
            "label": "mapping(uint256 => uint256[])"
          },
          "t_array(t_uint256)dyn_storage": {
            "label": "uint256[]"
          },
          "t_contract(Permissions)757": {
            "label": "contract Permissions"
          },
          "t_uint8": {
            "label": "uint8"
          }
        }
      }
    },
    "f6303b4c5fa75079f81fc6480eb3b894230d0ad5f018b901db05c4bfdb207695": {
      "address": "0x8FF215b2a8ea366c22117AA84621FdC3aC1A3a5a",
      "txHash": "0xdd9892b62426ee0877c7991263711cb3672dffc8e21019586d41ca1a38bc3c6f",
      "layout": {
        "solcVersion": "0.8.4",
        "storage": [
          {
            "contract": "Initializable",
            "label": "_initialized",
            "type": "t_uint8",
            "src": "../@openzeppelin/contracts-upgradeable/proxy/utils/Initializable.sol:63",
            "retypedFrom": "bool"
          },
          {
            "contract": "Initializable",
            "label": "_initializing",
            "type": "t_bool",
            "src": "../@openzeppelin/contracts-upgradeable/proxy/utils/Initializable.sol:68"
          },
          {
            "contract": "RevocationRegistry",
            "label": "registry",
            "type": "t_mapping(t_address,t_struct(WalletRevocationRegistry)1028_storage)",
            "src": "../project:/contracts/RevocationRegistry.sol:28"
          },
          {
            "contract": "RevocationRegistry",
            "label": "permissions",
            "type": "t_contract(Permissions)874",
            "src": "../project:/contracts/RevocationRegistry.sol:30"
          }
        ],
        "types": {
          "t_mapping(t_address,t_struct(WalletRevocationRegistry)1028_storage)": {
            "label": "mapping(address => struct RevocationRegistry.WalletRevocationRegistry)"
          },
          "t_address": {
            "label": "address"
          },
          "t_struct(WalletRevocationRegistry)1028_storage": {
            "label": "struct RevocationRegistry.WalletRevocationRegistry",
            "members": [
              {
                "label": "walletInRegistry",
                "type": "t_bool"
              },
              {
                "label": "totalLists",
                "type": "t_uint256"
              },
              {
                "label": "listIdUsage",
                "type": "t_mapping(t_uint256,t_bool)"
              },
              {
                "label": "lists",
                "type": "t_mapping(t_uint256,t_array(t_uint256)dyn_storage)"
              }
            ]
          },
          "t_bool": {
            "label": "bool"
          },
          "t_uint256": {
            "label": "uint256"
          },
          "t_mapping(t_uint256,t_bool)": {
            "label": "mapping(uint256 => bool)"
          },
          "t_mapping(t_uint256,t_array(t_uint256)dyn_storage)": {
            "label": "mapping(uint256 => uint256[])"
          },
          "t_array(t_uint256)dyn_storage": {
            "label": "uint256[]"
          },
          "t_contract(Permissions)874": {
            "label": "contract Permissions"
          },
          "t_uint8": {
            "label": "uint8"
          }
        }
      }
    },
    "0cc5b0f250986e208e7ec776b81307ad3f8c206a16c04c4dd89545cbb6f53da4": {
      "address": "0xb395c30088e43761D9c09A677094FdE066e79Cc9",
      "txHash": "0x1ea45b7dcf4aa2f6cb69aed3c1313fad557bdd1a8164d016e886e331afb3e03d",
      "layout": {
        "solcVersion": "0.8.4",
        "storage": [
          {
            "contract": "Initializable",
            "label": "_initialized",
            "type": "t_uint8",
            "src": "../@openzeppelin/contracts-upgradeable/proxy/utils/Initializable.sol:63",
            "retypedFrom": "bool"
          },
          {
            "contract": "Initializable",
            "label": "_initializing",
            "type": "t_bool",
            "src": "../@openzeppelin/contracts-upgradeable/proxy/utils/Initializable.sol:68"
          },
          {
            "contract": "RevocationRegistry",
            "label": "registry",
            "type": "t_mapping(t_address,t_struct(WalletRevocationRegistry)1512_storage)",
            "src": "../project:/contracts/RevocationRegistry.sol:28"
          },
          {
            "contract": "RevocationRegistry",
            "label": "permissions",
            "type": "t_contract(Permissions)1358",
            "src": "../project:/contracts/RevocationRegistry.sol:30"
          }
        ],
        "types": {
          "t_mapping(t_address,t_struct(WalletRevocationRegistry)1512_storage)": {
            "label": "mapping(address => struct RevocationRegistry.WalletRevocationRegistry)"
          },
          "t_address": {
            "label": "address"
          },
          "t_struct(WalletRevocationRegistry)1512_storage": {
            "label": "struct RevocationRegistry.WalletRevocationRegistry",
            "members": [
              {
                "label": "walletInRegistry",
                "type": "t_bool"
              },
              {
                "label": "totalLists",
                "type": "t_uint256"
              },
              {
                "label": "listIdUsage",
                "type": "t_mapping(t_uint256,t_bool)"
              },
              {
                "label": "lists",
                "type": "t_mapping(t_uint256,t_array(t_uint256)dyn_storage)"
              }
            ]
          },
          "t_bool": {
            "label": "bool"
          },
          "t_uint256": {
            "label": "uint256"
          },
          "t_mapping(t_uint256,t_bool)": {
            "label": "mapping(uint256 => bool)"
          },
          "t_mapping(t_uint256,t_array(t_uint256)dyn_storage)": {
            "label": "mapping(uint256 => uint256[])"
          },
          "t_array(t_uint256)dyn_storage": {
            "label": "uint256[]"
          },
          "t_contract(Permissions)1358": {
            "label": "contract Permissions"
          },
          "t_uint8": {
            "label": "uint8"
          }
        },
        "namespaces": {}
      }
    }
  }
}
